flakeheaven/__init__.py
flakeheaven/__main__.py
flakeheaven/_cli.py
flakeheaven/_constants.py
flakeheaven/_logic/__init__.py
flakeheaven/_logic/_baseline.py
flakeheaven/_logic/_colors.py
flakeheaven/_logic/_config.py
flakeheaven/_logic/_discover.py
flakeheaven/_logic/_extractors.py
flakeheaven/_logic/_plugin.py
flakeheaven/_logic/_snapshot.py
flakeheaven/_patched/__init__.py
flakeheaven/_patched/_app.py
flakeheaven/_patched/_checkers.py
flakeheaven/_patched/_plugins.py
flakeheaven/_patched/_processor.py
flakeheaven/_patched/_style_guide.py
flakeheaven/_patched/_violation.py
flakeheaven/_types.py
flakeheaven/_version.py
flakeheaven/commands/__init__.py
flakeheaven/commands/_baseline.py
flakeheaven/commands/_code.py
flakeheaven/commands/_codes.py
flakeheaven/commands/_config.py
flakeheaven/commands/_lint.py
flakeheaven/commands/_missed.py
flakeheaven/commands/_plugins.py
flakeheaven/commands/_version.py
flakeheaven/formatters/__init__.py
flakeheaven/formatters/_baseline.py
flakeheaven/formatters/_colored.py
flakeheaven/formatters/_gitlab.py
flakeheaven/formatters/_grouped.py
flakeheaven/formatters/_json.py
flakeheaven/formatters/_stat.py
flakeheaven/parsers/__init__.py
flakeheaven/parsers/_base.py
flakeheaven/parsers/_jupyter.py
flakeheaven/parsers/_markdown.py
flakeheaven/parsers/_python.py
flakeheaven/parsers/_rst.py
flakeheaven/parsers/_yaml.py
flakeheaven/plugins/__init__.py
flakeheaven/plugins/_pylint.py
flakeheaven-3.3.0.dist-info/LICENSE
flakeheaven-3.3.0.dist-info/METADATA
flakeheaven-3.3.0.dist-info/WHEEL
flakeheaven-3.3.0.dist-info/entry_points.txt
flakeheaven-3.3.0.dist-info/RECORD
