Metadata-Version: 2.1
Name: flakeheaven
Version: 3.3.0
Summary: FlakeHeaven is a [Flake8](https://gitlab.com/pycqa/flake8) wrapper to make it cool.
Home-page: https://github.com/flakeheaven/flakeheaven
License: MIT
Author: Gram
Author-email: master_fess@mail.ru
Requires-Python: >=3.7,<4.0
Classifier: Development Status :: 5 - Production/Stable
Classifier: Environment :: Console
Classifier: Framework :: Flake8
Classifier: Intended Audience :: Developers
Classifier: License :: OSI Approved :: MIT License
Classifier: Programming Language :: Python
Classifier: Programming Language :: Python :: 3
Classifier: Programming Language :: Python :: 3.7
Classifier: Programming Language :: Python :: 3.8
Classifier: Programming Language :: Python :: 3.9
Classifier: Programming Language :: Python :: 3.10
Classifier: Programming Language :: Python :: 3.11
Classifier: Programming Language :: Python :: 3
Classifier: Programming Language :: Python :: 3.7
Classifier: Programming Language :: Python :: 3.8
Classifier: Programming Language :: Python :: 3.9
Classifier: Topic :: Software Development :: Libraries :: Python Modules
Classifier: Topic :: Software Development :: Quality Assurance
Provides-Extra: docs
Requires-Dist: alabaster ; extra == "docs"
Requires-Dist: colorama
Requires-Dist: entrypoints
Requires-Dist: flake8 (>=4.0.1,<5.0.0)
Requires-Dist: importlib-metadata (>=1.0) ; python_version < "3.8"
Requires-Dist: myst-parser (>=0.18.0,<0.19.0) ; extra == "docs"
Requires-Dist: pygments
Requires-Dist: pygments-github-lexers ; extra == "docs"
Requires-Dist: sphinx ; extra == "docs"
Requires-Dist: toml
Requires-Dist: urllib3
Project-URL: Documentation, https://flakeheaven.readthedocs.io/
Project-URL: Repository, https://github.com/flakeheaven/flakeheaven
